{
    "section_01": {
        "issues": {
            "fluency": {
                "[SYNTAX]": [
                    "Occasionally complex sentence structures may impede immediate clarity for some readers."
                ],
                "[LEXICON]": [
                    "A few archaic expressions (e.g., \"ride Life's lists as a knight might ride\") might require additional processing for modern readers."
                ]
            },
            "coherence": {
                "[STRUCTURE]": [
                    "The text jumps between biographical narrative and art analysis without clear transitional phrases."
                ],
                "[CLARITY]": [
                    "Assumptions about the reader's prior knowledge of 18th-century art and figures (e.g., Gainsborough, Romney) could reduce clarity for uninformed readers."
                ]
            }
        },
        "scores": {
            "fluency": 4.5,
            "coherence": 4.0
        },
        "section_start_char_incl": 0,
        "section_end_char_excl": 8778,
        "section_summary": null
    },
    "section_02": {
        "issues": {
            "fluency": {
                "[SYNTAX]": [
                    "Complex sentence structures may impede smooth reading in some areas."
                ],
                "[LEXICON]": [
                    "Occasional use of less common vocabulary (e.g., \"comique\", \"pastellist\") might slow some readers."
                ]
            },
            "coherence": {
                "[TRANSITION]": [
                    "Abrupt shift from discussing Reynolds' success to generalizing about artists' personalities."
                ],
                "[CLARITY]": [
                    "The paragraph starting \"Perhaps the atmosphere...\" slightly distracts from the main narrative flow."
                ]
            }
        },
        "scores": {
            "fluency": 4.5,
            "coherence": 4.0
        },
        "section_start_char_incl": 8779,
        "section_end_char_excl": 12342,
        "section_summary": null
    }
}