{
    "section_01": {
        "issues": {
            "fluency": {
                "[GRAMMAR]": [
                    "minor punctuation errors"
                ],
                "[LEXICON]": [
                    "occasional use of outdated vocabulary"
                ],
                "[SYNTAX]": [
                    "some sentences are overly long and complex"
                ]
            },
            "coherence": {
                "[LOGIC]": [
                    "abrupt transition between paragraphs"
                ],
                "[STRUCTURE]": [
                    "non-chronological ordering of events"
                ],
                "[CLARITY]": [
                    "occasional ambiguity in sentence meaning"
                ]
            }
        },
        "scores": {
            "fluency": 4.5,
            "coherence": 4.0
        },
        "section_start_char_incl": 0,
        "section_end_char_excl": 8282,
        "section_summary": null
    },
    "section_02": {
        "issues": {
            "fluency": {
                "[GRAMMAR]": [
                    "minor punctuation errors"
                ],
                "[LEXICON]": [
                    "occasional word choice issues"
                ],
                "[SYNTAX]": [
                    "few sentence structure problems"
                ]
            },
            "coherence": {
                "[LOGIC]": [
                    "slight disconnect between some paragraphs"
                ],
                "[TRANSITION]": [
                    "occasional abrupt shifts in topic"
                ],
                "[CLARITY]": [
                    "minor ambiguity in some sentences"
                ]
            }
        },
        "scores": {
            "fluency": 4.5,
            "coherence": 4.0
        },
        "section_start_char_incl": 8283,
        "section_end_char_excl": 16551,
        "section_summary": null
    },
    "section_03": {
        "issues": {
            "fluency": {
                "[GRAMMAR]": [
                    "minor sentence structure issues"
                ],
                "[LEXICON]": [
                    "some word choices may be less common or slightly archaic"
                ],
                "[SYNTAX]": [
                    "occasional long or complex sentences"
                ]
            },
            "coherence": {
                "[LOGIC]": [
                    "some transitions between ideas could be smoother"
                ],
                "[STRUCTURE]": [
                    "the narrative jumps between different times and locations"
                ],
                "[CLARITY]": [
                    "a few sentences are wordy or contain multiple ideas"
                ]
            }
        },
        "scores": {
            "fluency": 4.5,
            "coherence": 4.0
        },
        "section_start_char_incl": 16551,
        "section_end_char_excl": 24746,
        "section_summary": null
    },
    "section_04": {
        "issues": {
            "fluency": {
                "[GRAMMAR]": [
                    "minor punctuation errors"
                ],
                "[LEXICON]": [
                    "some word choices may be less common or slightly archaic"
                ],
                "[SYNTAX]": [
                    "a few long, winding sentences"
                ]
            },
            "coherence": {
                "[LOGIC]": [
                    "occasional jumps in narrative flow"
                ],
                "[TRANSITION]": [
                    "some transitions between ideas or scenes feel abrupt"
                ],
                "[CLARITY]": [
                    "a few sentences or phrases are wordy or unclear"
                ]
            }
        },
        "scores": {
            "fluency": 4.5,
            "coherence": 4.0
        },
        "section_start_char_incl": 24747,
        "section_end_char_excl": 33075,
        "section_summary": null
    },
    "section_05": {
        "issues": {
            "fluency": {
                "[GRAMMAR]": [
                    "minor sentence structure issues"
                ],
                "[LEXICON]": [
                    "some word choices may be less common or slightly archaic"
                ]
            },
            "coherence": {
                "[STRUCTURE]": [
                    "occasional jumps in narrative or introduction of new characters without full context"
                ],
                "[CLARITY]": [
                    "a few sentences are wordy or contain multiple ideas, potentially reducing clarity"
                ]
            }
        },
        "scores": {
            "fluency": 4.5,
            "coherence": 4.0
        },
        "section_start_char_incl": 33076,
        "section_end_char_excl": 41510,
        "section_summary": null
    },
    "section_06": {
        "issues": {
            "fluency": {
                "[GRAMMAR]": [
                    "minor sentence structure issues"
                ],
                "[LEXICON]": [
                    "occasional use of outdated vocabulary"
                ],
                "[SYNTAX]": [
                    "some sentences are wordy or convoluted"
                ]
            },
            "coherence": {
                "[LOGIC]": [
                    "occasional abrupt shifts in topic"
                ],
                "[TRANSITION]": [
                    "sometimes lacks smooth connections between ideas"
                ],
                "[CLARITY]": [
                    "a few sentences are unclear or confusing"
                ]
            }
        },
        "scores": {
            "fluency": 4.5,
            "coherence": 4.0
        },
        "section_start_char_incl": 41511,
        "section_end_char_excl": 49982,
        "section_summary": null
    },
    "section_07": {
        "issues": {
            "fluency": {
                "[GRAMMAR]": [
                    "minor sentence structure issues"
                ],
                "[LEXICON]": [
                    "occasional word choice awkwardness"
                ],
                "[SYNTAX]": [
                    "few instances of complex sentence structures"
                ]
            },
            "coherence": {
                "[LOGIC]": [
                    "slight disconnect between some paragraphs"
                ],
                "[TRANSITION]": [
                    "occasional abrupt shifts in topic"
                ],
                "[CLARITY]": [
                    "minor ambiguity in a few sentences"
                ]
            }
        },
        "scores": {
            "fluency": 4.5,
            "coherence": 4.0
        },
        "section_start_char_incl": 49983,
        "section_end_char_excl": 58475,
        "section_summary": null
    },
    "section_08": {
        "issues": {
            "fluency": {
                "[GRAMMAR]": [
                    "minor punctuation errors"
                ],
                "[LEXICON]": [
                    "some complex vocabulary"
                ],
                "[SYNTAX]": [
                    "occasional long sentences"
                ]
            },
            "coherence": {
                "[LOGIC]": [
                    "abrupt shift between story and descriptive passage"
                ],
                "[STRUCTURE]": [
                    "lack of clear transitions between ideas"
                ],
                "[CLARITY]": [
                    "some sentences are wordy or unclear"
                ]
            }
        },
        "scores": {
            "fluency": 4.0,
            "coherence": 3.5
        },
        "section_start_char_incl": 58476,
        "section_end_char_excl": 66812,
        "section_summary": null
    },
    "section_09": {
        "issues": {
            "fluency": {
                "[GRAMMAR]": [
                    "minor sentence structure issues"
                ],
                "[LEXICON]": [
                    "occasional word choice could be more precise"
                ],
                "[SYNTAX]": [
                    "a few long sentences may hinder smooth reading"
                ]
            },
            "coherence": {
                "[LOGIC]": [
                    "some transitions between ideas could be smoother"
                ],
                "[STRUCTURE]": [
                    "the narrative jumps slightly between hospital descriptions and the need for a supplementary kitchen"
                ],
                "[CLARITY]": [
                    "a few sentences are wordy or contain multiple ideas, potentially causing confusion"
                ]
            }
        },
        "scores": {
            "fluency": 4.5,
            "coherence": 4.0
        },
        "section_start_char_incl": 66813,
        "section_end_char_excl": 75219,
        "section_summary": null
    },
    "section_10": {
        "issues": {
            "fluency": {
                "[GRAMMAR]": [
                    "minor punctuation errors"
                ],
                "[LEXICON]": [
                    "occasional word choice issues"
                ],
                "[SYNTAX]": [
                    "some sentence structures are complex"
                ]
            },
            "coherence": {
                "[LOGIC]": [
                    "a few abrupt transitions between ideas"
                ],
                "[STRUCTURE]": [
                    "some paragraphs lack clear topic sentences"
                ],
                "[CLARITY]": [
                    "occasional ambiguity in sentence meaning"
                ]
            }
        },
        "scores": {
            "fluency": 4.5,
            "coherence": 4.0
        },
        "section_start_char_incl": 75220,
        "section_end_char_excl": 82329,
        "section_summary": null
    }
}