{
    "section_01": {
        "issues": {
            "fluency": {
                "[SYNTAX]": [
                    "Complex sentence structures may impede smooth reading for some readers."
                ],
                "[LEXICON]": [
                    "Archaic or less common vocabulary (e.g., \"huckster\", \"fourpence-halfpenny\") might require additional effort for comprehension."
                ]
            },
            "coherence": {
                "[STRUCTURE]": [
                    "Abrupt transition between the anecdote about the bookowner and the subsequent literary critiques."
                ],
                "[CLARITY]": [
                    "Some paragraphs lack a clear connection to the preceding or following text, potentially confusing the reader about the section's overall focus."
                ]
            }
        },
        "scores": {
            "fluency": 4.0,
            "coherence": 3.5
        },
        "section_start_char_incl": 0,
        "section_end_char_excl": 7862,
        "section_summary": null
    },
    "section_02": {
        "issues": {
            "fluency": {
                "[LEXICON]": [
                    "Overly complex vocabulary in some passages (e.g., \"tombstone\", \"inconsequence\", \"genuinely\") may hinder readability for non-specialist readers."
                ],
                "[SYNTAX]": [
                    "Occasional long, winding sentences (e.g., the paragraph starting with \"The bookman has a series...\") could improve with clearer structuring."
                ]
            },
            "coherence": {
                "[STRUCTURE]": [
                    "Abrupt transition from discussing literary preferences to providing historical details about the Mescalero Apaches without clear contextualization."
                ],
                "[LOGIC]": [
                    "The narrative jumps between personal anecdotes, literary critiques, and historical information, sometimes feeling disjointed."
                ]
            }
        },
        "scores": {
            "fluency": 4.0,
            "coherence": 3.5
        },
        "section_start_char_incl": 7862,
        "section_end_char_excl": 15913,
        "section_summary": null
    },
    "section_03": {
        "issues": {
            "fluency": {
                "[SYNTAX]": [
                    "Abrupt transition between philosophical discussion and literary critique (e.g., shift from Von Eicken to Esmond's thoughts)"
                ],
                "[LEXICON]": [
                    "Overly complex vocabulary may hinder smooth reading for non-expert readers (e.g., \"defunct\", \"salutary cold douche\")"
                ],
                "[GRAMMAR]": [
                    "Minor punctuation inconsistencies (e.g., missing Oxford commas in lists)"
                ]
            },
            "coherence": {
                "[STRUCTURE]": [
                    "Non-sequential topic shifts (philosophy, literature, personal anecdotes, book collecting)"
                ],
                "[TRANSITION]": [
                    "Lack of clear connectors between distinct thematic sections"
                ],
                "[LOGIC]": [
                    "Tangential examples (e.g., the bookman's rearrangement habits) somewhat detract from central themes"
                ]
            }
        },
        "scores": {
            "fluency": 4.0,
            "coherence": 3.5
        },
        "section_start_char_incl": 15913,
        "section_end_char_excl": 24278,
        "section_summary": null
    },
    "section_04": {
        "issues": {
            "fluency": {
                "[SYNTAX]": [
                    "Abrupt transition between \"Last week I saw such a case...\" and the preceding paragraph about the bookman's habits.",
                    "Long, winding sentence structures (e.g., the paragraph describing the bookman's sacrifices) may impede fluent reading."
                ],
                "[LEXICON]": [
                    "Overly complex vocabulary in some passages (e.g., \"reking with infection\", \"disinfectant\", \"commercial conversation\") may hinder smooth reading for non-expert readers."
                ],
                "[GRAMMAR]": [
                    "Missing article before \"certain shop\" (should be \"a certain shop\" for consistency)."
                ]
            },
            "coherence": {
                "[STRUCTURE]": [
                    "Sudden, unconnected introduction of \"The matter transmitter\" and philosophical quotes near the end, disrupting the cohesive theme of book collecting."
                ],
                "[LOGIC]": [
                    "The narrative jumps illogically from discussing bookmen to a science fiction element (\"The matter transmitter\") without context or transition."
                ],
                "[CLARITY]": [
                    "The purpose and relevance of the quote about \"sanctified Mirrors\" are unclear in the context of the surrounding text."
                ],
                "[TRANSITION]": [
                    "Lack of transitional phrases or sentences when shifting from one idea to another (e.g., from the bookman's habits to the example of seeing such a case)."
                ]
            }
        },
        "scores": {
            "fluency": 3.5,
            "coherence": 2.5
        },
        "section_start_char_incl": 24278,
        "section_end_char_excl": 32585,
        "section_summary": null
    }
}