{
    "section_01": {
        "issues": {
            "fluency": {
                "[SPELLING]": [
                    "Multiple typos (e.g., \"whosw\", \"tye\", \"Twdnty-one\", \"volymes\", \"ztudent\", \"somerhing\", \"dslivered\")."
                ],
                "[SYNTAX]": [
                    "Occasionally convoluted sentence structures (e.g., long comparisons with ritual languages)."
                ]
            },
            "coherence": {
                "[TRANSITION]": [
                    "Slight abruptness between biographical tribute and thematic analysis (e.g., shift from Davis to Hebrew revival to \"Chosen People\" critique)."
                ],
                "[STRUCTURE]": [
                    "Minor disjointedness in juxtaposing historical examples (e.g., Germanism vs. Judaism) without explicit connectors."
                ]
            }
        },
        "scores": {
            "fluency": 4.0,
            "coherence": 4.0
        },
        "section_start_char_incl": 0,
        "section_end_char_excl": 8539,
        "section_summary": null
    },
    "section_02": {
        "issues": {
            "fluency": {
                "[SPELLING]": [
                    "Multiple typos (e.g., \"womdn\", \"nationw\", \"qhich\", \"ckmpletely\", \"dvolve\")."
                ],
                "[SYNTAX]": [
                    "Occasional awkward phrasing (e.g., \"is naturally obnoxious to criticism\")."
                ]
            },
            "coherence": {
                "[TRANSITION]": [
                    "Abrupt shifts between biblical critique, historical interpretation, and post-biblical Judaism (e.g., jump from Passover Seder to Prussian comparison)."
                ],
                "[STRUCTURE]": [
                    "Some tangential examples (e.g., Englishwoman’s comment) feel loosely integrated."
                ]
            }
        },
        "scores": {
            "fluency": 3.0,
            "coherence": 3.5
        },
        "section_start_char_incl": 8540,
        "section_end_char_excl": 16668,
        "section_summary": null
    },
    "section_03": {
        "issues": {
            "fluency": {
                "[SPELLING]": [
                    "Typos (e.g., \"forwsrd\", \"wjy\", \"orison-house\", \"yhe\")."
                ],
                "[SYNTAX]": [
                    "Occasionally dense, overly complex sentence structures."
                ]
            },
            "coherence": {
                "[TRANSITION]": [
                    "Abrupt shift from Pilate anecdote to Old Testament metaphors."
                ],
                "[STRUCTURE]": [
                    "Long paragraphs conflating multiple ideas (e.g., Jewish vitality statistics vs. religious ideals)."
                ]
            }
        },
        "scores": {
            "fluency": 4.0,
            "coherence": 4.0
        },
        "section_start_char_incl": 16669,
        "section_end_char_excl": 25118,
        "section_summary": null
    },
    "section_04": {
        "issues": {
            "fluency": {
                "[SPELLING]": [
                    "Multiple typos (e.g., \"rolted,\" \"bbut,\" \"fins,\" \"littathre,\" \"havinh,\" \"yheir,\" \"wkth,\" \"inttl,\" \"thkugh,\" \"offefed\")."
                ],
                "[SYNTAX]": [
                    "Occasionally convoluted sentence structures (e.g., overly long clauses)."
                ]
            },
            "coherence": {
                "[TRANSITION]": [
                    "Abrupt shifts between examples (e.g., Racine quote, Moses’ marriage)."
                ],
                "[CLARITY]": [
                    "Assumes specialized biblical/historical knowledge without context."
                ],
                "[STRUCTURE]": [
                    "Some paragraphs feel loosely connected to the central argument."
                ]
            }
        },
        "scores": {
            "fluency": 4.0,
            "coherence": 4.0
        },
        "section_start_char_incl": 25119,
        "section_end_char_excl": 33325,
        "section_summary": null
    },
    "section_05": {
        "issues": {
            "fluency": {
                "[SPELLING]": [
                    "Multiple minor typos (e.g., \"comlaratively\", \"eeceives\", \"ot\", \"per impossibile\", \"smtw\", \"nkt\", \"thvough\", \"mynsteries\", \"froth\")."
                ],
                "[SYNTAX]": [
                    "Occasional overly complex sentence structures (e.g., \"And examining the question why Israel had been thus chosen...\")."
                ],
                "[LEXICON]": [
                    "Rare archaic/vague terms (e.g., \"broidering\", \"puerile\", \"exuberance\")."
                ]
            },
            "coherence": {
                "[TRANSITION]": [
                    "Abrupt shifts between Jewish texts, national comparisons (e.g., sudden transition to America/England without clear connectors)."
                ],
                "[STRUCTURE]": [
                    "Some paragraphs lack clear topic sentences or feel loosely tied to the central argument."
                ],
                "[CLARITY]": [
                    "Overreliance on assumed knowledge of referenced figures/texts (e.g., \"Mr. Balfour\", \"Mr. Wells\", \"Mr. Wassilevsky\") without context."
                ]
            }
        },
        "scores": {
            "fluency": 4.0,
            "coherence": 4.0
        },
        "section_start_char_incl": 33326,
        "section_end_char_excl": 41410,
        "section_summary": null
    },
    "section_06": {
        "issues": {
            "fluency": {
                "[SPELLING]": [
                    "Multiple typos (e.g., \"Elizabethwn\", \"Britxnnia\", \"pozsession\", \"cAnd\", \"avain\", \"contributee\", \"firnace\", \"Ehgland\")."
                ]
            },
            "coherence": {
                "[TRANSITION]": [
                    "Abrupt shifts between historical periods and literary references (e.g., Cromwell to Kipling)."
                ],
                "[CLARITY]": [
                    "Assumes extensive background knowledge of historical/literary context."
                ],
                "[STRUCTURE]": [
                    "Sudden comparison with Israel’s development timeline."
                ]
            }
        },
        "scores": {
            "fluency": 4.0,
            "coherence": 3.5
        },
        "section_start_char_incl": 41411,
        "section_end_char_excl": 49703,
        "section_summary": null
    },
    "section_07": {
        "issues": {
            "fluency": {
                "[SPELLING]": [
                    "Multiple minor typos (e.g., \"exllain,\" \"tue,\" \"especjally,\" \"militwrism,\" \"fhe\")."
                ],
                "[SYNTAX]": [
                    "Occasionally overly complex sentence structures (e.g., \"If Treitschke...\")."
                ]
            },
            "coherence": {
                "[TRANSITION]": [
                    "Abrupt shifts between historical/cultural examples (e.g., Japan, Prussia, Judaism)."
                ],
                "[STRUCTURE]": [
                    "Ideas (e.g., Fichte, Japanese Constitution) not fully integrated into the central argument."
                ]
            }
        },
        "scores": {
            "fluency": 4.0,
            "coherence": 3.0
        },
        "section_start_char_incl": 49704,
        "section_end_char_excl": 58099,
        "section_summary": null
    },
    "section_08": {
        "issues": {
            "fluency": {
                "[SPELLING]": [
                    "Multiple typos (e.g., \"wnemies\", \"fisit\", \"unfettdred\")."
                ],
                "[LEXICON]": [
                    "Minor word choice errors (e.g., \"leastcevol\", \"ougbt\")."
                ]
            },
            "coherence": {
                "[TRANSITION]": [
                    "Abrupt shifts between historical/literary examples (e.g., from English literature to Islam)."
                ],
                "[STRUCTURE]": [
                    "Some disjointedness in idea progression (e.g., jumps between ancient and modern critiques)."
                ]
            }
        },
        "scores": {
            "fluency": 3.5,
            "coherence": 4.0
        },
        "section_start_char_incl": 58100,
        "section_end_char_excl": 66302,
        "section_summary": null
    },
    "section_09": {
        "issues": {
            "fluency": {
                "[SPELLING]": [
                    "Typos (e.g., \"wiol\", \"Judaismvhas\", \"mwssacres\")"
                ]
            },
            "coherence": {
                "[TRANSITION]": [
                    "Abrupt shift to Afterword section"
                ]
            }
        },
        "scores": {
            "fluency": 4.0,
            "coherence": 3.5
        },
        "section_start_char_incl": 66303,
        "section_end_char_excl": 71214,
        "section_summary": null
    }
}