{
    "section_01": {
        "issues": {
            "fluency": {
                "[GRAMMAR]": [
                    "\"Of the historic and scenic charms of the thing much has already been written...\"",
                    "\"so that little American cousins may be expected to have at least a nodding acquaintance with them.\"",
                    "\"On the other hand, these charms are so numerous and varied that American cousins cannot but wish...\"",
                    "\"The two lads ran across the garden and burst into the sitting-room where Doctor Gordon and Mrs. Gordon were having afternoon tea.\"",
                    "\"He may stay in the armchair by the fire until I can find a basket for him to sleep in\"",
                    "\"The boys were soon there as well, for the tea at half-past four in the afternoon is the favourite meal...\"",
                    "\"There are such good things to eat then! First, there is shortbread...\"",
                    "\"and fluted around the edge,--all children know that pattern,--hot from the oven...\"",
                    "\"He has invited the thing, also; but I must warn him\""
                ],
                "[SPELLING]": [
                    "\"a stuff and Burns\" (appears multiple times)"
                ]
            },
            "coherence": {
                "[LOGIC]": [
                    "Confusing references to \"the thing\" and \"a stuff\" that appear multiple times without clear context",
                    "The narrative about the puppy is interrupted by detailed descriptions of Scottish cuisine that seem unrelated",
                    "The text mentions \"the thing\" and \"a stuff\" multiple times without clarifying what these refer to",
                    "The narrative about the Gordon family's tea is disconnected from the main story about finding the puppy"
                ],
                "[CLARITY]": [
                    "Sudden shifts between narrative and descriptive passages without clear transitions",
                    "The relationship between the puppy story and the broader theme of Scottish-American connections is unclear"
                ],
                "[STRUCTURE]": [
                    "The text moves abruptly from the story of finding the puppy to descriptions of Scottish food without clear connection",
                    "The transition from the puppy story to the description of afternoon tea is abrupt and unexplained"
                ]
            }
        },
        "scores": {
            "fluency": 3.0,
            "coherence": 3.5
        },
        "section_start_char_incl": 0,
        "section_end_char_excl": 7940,
        "section_summary": null
    },
    "section_02": {
        "issues": {
            "fluency": {
                "[GRAMMAR]": [
                    "\"He had gone to a thing when he was a young lad\" (incorrect use of \"a thing\")",
                    "\"and had made a great fortune in copper mines\" (awkward phrasing)",
                    "\"He wanted to enjoy it in the stuff, his own country\" (confusing and incorrect use of \"in the stuff\")",
                    "\"as a lake is called in a thing\" (incorrect use of \"a thing\")"
                ],
                "[SPELLING]": [
                    "\"a thing\" (repeated multiple times in place of specific terms)",
                    "\"doggie\" (informal and inconsistent with the rest of the text)"
                ],
                "[SYNTAX]": [
                    "\"To Donald it seemed a palace, and he did not think the king himself had anything so grand\" (awkward word order)",
                    "\"There were several clear streams and a loch, as a lake is called in a thing\" (awkward and confusing phrasing)"
                ],
                "[LEXICON]": [
                    "\"a thing\" (used in place of specific terms like \"America\" or \"Scotland\")"
                ]
            },
            "coherence": {
                "[LOGIC]": [
                    "Sudden shift from the boys' excitement about their cousins to Donald's memories of his uncle's adventures in America",
                    "The mention of the puppy appears out of context and is not clearly connected to the previous discussion about Donald's uncle and the Highlands"
                ],
                "[STRUCTURE]": [
                    "The paragraph about Donald rushing home from school and naming the puppy feels disconnected from the previous narrative about his uncle and the Highlands"
                ],
                "[CLARITY]": [
                    "The repeated use of \"a thing\" instead of specific terms creates confusion and disrupts the narrative flow"
                ],
                "[TRANSITION]": [
                    "The transition from the description of the estate to the story of the puppy is abrupt and lacks a clear connection"
                ]
            }
        },
        "scores": {
            "fluency": 3.5,
            "coherence": 3.5
        },
        "section_start_char_incl": 7940,
        "section_end_char_excl": 11802,
        "section_summary": null
    }
}