[
    {
        "id": "JM-41497_C_2_24",
        "manipulated_text": "/data/project_gutenberg/manipulated_pg-1900_full/C/2/24/paragraph/exp_1/JM-41497.txt",
        "manipulated_char_spans": [
            [
                23883,
                23883
            ],
            [
                30220,
                30220
            ],
            [
                23243,
                23243
            ],
            [
                10130,
                10130
            ],
            [
                33856,
                33856
            ],
            [
                4103,
                4103
            ],
            [
                5212,
                5212
            ],
            [
                1440,
                1440
            ],
            [
                21907,
                21907
            ]
        ],
        "range_type": "paragraph",
        "affected_metric": "coherence",
        "manipulation_category": "plot_inconsistencies",
        "manipulation_type": "temporal_inconsistencies",
        "gold_id": "JM-41497",
        "gold_text": "/data/project_gutenberg/gold_dataset/PG-41497.txt",
        "random_seed": 31,
        "params": {
            "n": 0,
            "min_len": 50,
            "repetition_factor": null,
            "start": 0,
            "end": 0,
            "ratio": true,
            "entity": null,
            "entities_to_consider": [
                "LOC",
                "GPE",
                "FAC",
                "ORG"
            ],
            "replacement_terms": [
                "stuff",
                "thing"
            ]
        }
    },
    {
        "id": "JM-36072_C_2_24",
        "manipulated_text": "/data/project_gutenberg/manipulated_pg-1900_full/C/2/24/paragraph/exp_1/JM-36072.txt",
        "manipulated_char_spans": [
            [
                21896,
                21896
            ],
            [
                37399,
                37399
            ],
            [
                49222,
                49222
            ],
            [
                6347,
                6347
            ],
            [
                6056,
                6056
            ],
            [
                18009,
                18009
            ],
            [
                32297,
                32297
            ],
            [
                13453,
                13453
            ],
            [
                21480,
                21480
            ]
        ],
        "range_type": "paragraph",
        "affected_metric": "coherence",
        "manipulation_category": "plot_inconsistencies",
        "manipulation_type": "temporal_inconsistencies",
        "gold_id": "JM-36072",
        "gold_text": "/data/project_gutenberg/gold_dataset/PG-36072.txt",
        "random_seed": 31,
        "params": {
            "n": 0,
            "min_len": 50,
            "repetition_factor": null,
            "start": 0,
            "end": 0,
            "ratio": true,
            "entity": null,
            "entities_to_consider": [
                "LOC",
                "GPE",
                "FAC",
                "ORG"
            ],
            "replacement_terms": [
                "stuff",
                "thing"
            ]
        }
    },
    {
        "id": "JM-19281_C_2_24",
        "manipulated_text": "/data/project_gutenberg/manipulated_pg-1900_full/C/2/24/paragraph/exp_1/JM-19281.txt",
        "manipulated_char_spans": [
            [
                16012,
                16012
            ],
            [
                50205,
                50205
            ],
            [
                57117,
                57117
            ],
            [
                49110,
                49110
            ],
            [
                86585,
                86585
            ],
            [
                64016,
                64016
            ],
            [
                25638,
                25638
            ],
            [
                5923,
                5923
            ],
            [
                17294,
                17294
            ],
            [
                1969,
                1969
            ],
            [
                79426,
                79426
            ],
            [
                55641,
                55641
            ],
            [
                34781,
                34781
            ],
            [
                67448,
                67448
            ]
        ],
        "range_type": "paragraph",
        "affected_metric": "coherence",
        "manipulation_category": "plot_inconsistencies",
        "manipulation_type": "temporal_inconsistencies",
        "gold_id": "JM-19281",
        "gold_text": "/data/project_gutenberg/gold_dataset/PG-19281.txt",
        "random_seed": 31,
        "params": {
            "n": 0,
            "min_len": 50,
            "repetition_factor": null,
            "start": 0,
            "end": 0,
            "ratio": true,
            "entity": null,
            "entities_to_consider": [
                "LOC",
                "GPE",
                "FAC",
                "ORG"
            ],
            "replacement_terms": [
                "stuff",
                "thing"
            ]
        }
    },
    {
        "id": "JM-29146_C_2_24",
        "manipulated_text": "/data/project_gutenberg/manipulated_pg-1900_full/C/2/24/paragraph/exp_1/JM-29146.txt",
        "manipulated_char_spans": [
            [
                73806,
                73806
            ],
            [
                63685,
                63685
            ],
            [
                50586,
                50586
            ],
            [
                35800,
                35800
            ],
            [
                51366,
                51366
            ],
            [
                37386,
                37386
            ],
            [
                16881,
                16881
            ],
            [
                42227,
                42227
            ],
            [
                15704,
                15704
            ],
            [
                56135,
                56135
            ],
            [
                39901,
                39901
            ],
            [
                75905,
                75905
            ],
            [
                23247,
                23247
            ]
        ],
        "range_type": "paragraph",
        "affected_metric": "coherence",
        "manipulation_category": "plot_inconsistencies",
        "manipulation_type": "temporal_inconsistencies",
        "gold_id": "JM-29146",
        "gold_text": "/data/project_gutenberg/gold_dataset/PG-29146.txt",
        "random_seed": 31,
        "params": {
            "n": 0,
            "min_len": 50,
            "repetition_factor": null,
            "start": 0,
            "end": 0,
            "ratio": true,
            "entity": null,
            "entities_to_consider": [
                "LOC",
                "GPE",
                "FAC",
                "ORG"
            ],
            "replacement_terms": [
                "stuff",
                "thing"
            ]
        }
    },
    {
        "id": "JM-60129_C_2_24",
        "manipulated_text": "/data/project_gutenberg/manipulated_pg-1900_full/C/2/24/paragraph/exp_1/JM-60129.txt",
        "manipulated_char_spans": [
            [
                11280,
                11280
            ],
            [
                17207,
                17207
            ],
            [
                29369,
                29369
            ],
            [
                21490,
                21490
            ],
            [
                15143,
                15143
            ],
            [
                35214,
                35214
            ],
            [
                61849,
                61849
            ],
            [
                47996,
                47996
            ],
            [
                52417,
                52417
            ],
            [
                70283,
                70283
            ],
            [
                19318,
                19318
            ],
            [
                66089,
                66089
            ],
            [
                74177,
                74177
            ],
            [
                4359,
                4359
            ]
        ],
        "range_type": "paragraph",
        "affected_metric": "coherence",
        "manipulation_category": "plot_inconsistencies",
        "manipulation_type": "temporal_inconsistencies",
        "gold_id": "JM-60129",
        "gold_text": "/data/project_gutenberg/gold_dataset/PG-60129.txt",
        "random_seed": 31,
        "params": {
            "n": 0,
            "min_len": 50,
            "repetition_factor": null,
            "start": 0,
            "end": 0,
            "ratio": true,
            "entity": null,
            "entities_to_consider": [
                "LOC",
                "GPE",
                "FAC",
                "ORG"
            ],
            "replacement_terms": [
                "stuff",
                "thing"
            ]
        }
    },
    {
        "id": "JM-52760_C_2_24",
        "manipulated_text": "/data/project_gutenberg/manipulated_pg-1900_full/C/2/24/paragraph/exp_1/JM-52760.txt",
        "manipulated_char_spans": [
            [
                3970,
                3970
            ],
            [
                51413,
                51413
            ],
            [
                44664,
                44664
            ],
            [
                24057,
                24057
            ],
            [
                29785,
                29785
            ],
            [
                26099,
                26099
            ],
            [
                37955,
                37955
            ],
            [
                41033,
                41033
            ],
            [
                35354,
                35354
            ],
            [
                42242,
                42242
            ],
            [
                15493,
                15493
            ],
            [
                26355,
                26355
            ]
        ],
        "range_type": "paragraph",
        "affected_metric": "coherence",
        "manipulation_category": "plot_inconsistencies",
        "manipulation_type": "temporal_inconsistencies",
        "gold_id": "JM-52760",
        "gold_text": "/data/project_gutenberg/gold_dataset/PG-52760.txt",
        "random_seed": 31,
        "params": {
            "n": 0,
            "min_len": 50,
            "repetition_factor": null,
            "start": 0,
            "end": 0,
            "ratio": true,
            "entity": null,
            "entities_to_consider": [
                "LOC",
                "GPE",
                "FAC",
                "ORG"
            ],
            "replacement_terms": [
                "stuff",
                "thing"
            ]
        }
    },
    {
        "id": "JM-26145_C_2_24",
        "manipulated_text": "/data/project_gutenberg/manipulated_pg-1900_full/C/2/24/paragraph/exp_1/JM-26145.txt",
        "manipulated_char_spans": [
            [
                4184,
                4184
            ],
            [
                10893,
                10893
            ],
            [
                45025,
                45025
            ],
            [
                19940,
                19940
            ],
            [
                32435,
                32435
            ],
            [
                68846,
                68846
            ],
            [
                43500,
                43500
            ],
            [
                70239,
                70239
            ],
            [
                1486,
                1486
            ],
            [
                31551,
                31551
            ],
            [
                37938,
                37938
            ],
            [
                30635,
                30635
            ],
            [
                65547,
                65547
            ]
        ],
        "range_type": "paragraph",
        "affected_metric": "coherence",
        "manipulation_category": "plot_inconsistencies",
        "manipulation_type": "temporal_inconsistencies",
        "gold_id": "JM-26145",
        "gold_text": "/data/project_gutenberg/gold_dataset/PG-26145.txt",
        "random_seed": 31,
        "params": {
            "n": 0,
            "min_len": 50,
            "repetition_factor": null,
            "start": 0,
            "end": 0,
            "ratio": true,
            "entity": null,
            "entities_to_consider": [
                "LOC",
                "GPE",
                "FAC",
                "ORG"
            ],
            "replacement_terms": [
                "stuff",
                "thing"
            ]
        }
    },
    {
        "id": "JM-20631_C_2_24",
        "manipulated_text": "/data/project_gutenberg/manipulated_pg-1900_full/C/2/24/paragraph/exp_1/JM-20631.txt",
        "manipulated_char_spans": [
            [
                27687,
                27687
            ],
            [
                71214,
                71214
            ],
            [
                1764,
                1764
            ],
            [
                40333,
                40333
            ],
            [
                18928,
                18928
            ],
            [
                46819,
                46819
            ],
            [
                41992,
                41992
            ],
            [
                46919,
                46919
            ],
            [
                9587,
                9587
            ],
            [
                4205,
                4205
            ],
            [
                976,
                976
            ],
            [
                44595,
                44595
            ]
        ],
        "range_type": "paragraph",
        "affected_metric": "coherence",
        "manipulation_category": "plot_inconsistencies",
        "manipulation_type": "temporal_inconsistencies",
        "gold_id": "JM-20631",
        "gold_text": "/data/project_gutenberg/gold_dataset/PG-20631.txt",
        "random_seed": 31,
        "params": {
            "n": 0,
            "min_len": 50,
            "repetition_factor": null,
            "start": 0,
            "end": 0,
            "ratio": true,
            "entity": null,
            "entities_to_consider": [
                "LOC",
                "GPE",
                "FAC",
                "ORG"
            ],
            "replacement_terms": [
                "stuff",
                "thing"
            ]
        }
    },
    {
        "id": "JM-63426_C_2_24",
        "manipulated_text": "/data/project_gutenberg/manipulated_pg-1900_full/C/2/24/paragraph/exp_1/JM-63426.txt",
        "manipulated_char_spans": [
            [
                79777,
                79777
            ],
            [
                71884,
                71884
            ],
            [
                79589,
                79589
            ],
            [
                15498,
                15498
            ],
            [
                10476,
                10476
            ],
            [
                63920,
                63920
            ],
            [
                33136,
                33136
            ],
            [
                42873,
                42873
            ],
            [
                18492,
                18492
            ],
            [
                22058,
                22058
            ],
            [
                29626,
                29626
            ],
            [
                87244,
                87244
            ],
            [
                83624,
                83624
            ],
            [
                37555,
                37555
            ],
            [
                76171,
                76171
            ]
        ],
        "range_type": "paragraph",
        "affected_metric": "coherence",
        "manipulation_category": "plot_inconsistencies",
        "manipulation_type": "temporal_inconsistencies",
        "gold_id": "JM-63426",
        "gold_text": "/data/project_gutenberg/gold_dataset/PG-63426.txt",
        "random_seed": 31,
        "params": {
            "n": 0,
            "min_len": 50,
            "repetition_factor": null,
            "start": 0,
            "end": 0,
            "ratio": true,
            "entity": null,
            "entities_to_consider": [
                "LOC",
                "GPE",
                "FAC",
                "ORG"
            ],
            "replacement_terms": [
                "stuff",
                "thing"
            ]
        }
    },
    {
        "id": "JM-62589_C_2_24",
        "manipulated_text": "/data/project_gutenberg/manipulated_pg-1900_full/C/2/24/paragraph/exp_1/JM-62589.txt",
        "manipulated_char_spans": [
            [
                16982,
                16982
            ],
            [
                12399,
                12399
            ],
            [
                81770,
                81770
            ],
            [
                11197,
                11197
            ],
            [
                76969,
                76969
            ],
            [
                30265,
                30265
            ],
            [
                25192,
                25192
            ],
            [
                72542,
                72542
            ],
            [
                45463,
                45463
            ],
            [
                43321,
                43321
            ],
            [
                19200,
                19200
            ],
            [
                7314,
                7314
            ],
            [
                54064,
                54064
            ],
            [
                9180,
                9180
            ],
            [
                32277,
                32277
            ]
        ],
        "range_type": "paragraph",
        "affected_metric": "coherence",
        "manipulation_category": "plot_inconsistencies",
        "manipulation_type": "temporal_inconsistencies",
        "gold_id": "JM-62589",
        "gold_text": "/data/project_gutenberg/gold_dataset/PG-62589.txt",
        "random_seed": 31,
        "params": {
            "n": 0,
            "min_len": 50,
            "repetition_factor": null,
            "start": 0,
            "end": 0,
            "ratio": true,
            "entity": null,
            "entities_to_consider": [
                "LOC",
                "GPE",
                "FAC",
                "ORG"
            ],
            "replacement_terms": [
                "stuff",
                "thing"
            ]
        }
    },
    {
        "id": "JM-43546_C_2_24",
        "manipulated_text": "/data/project_gutenberg/manipulated_pg-1900_full/C/2/24/paragraph/exp_1/JM-43546.txt",
        "manipulated_char_spans": [
            [
                38435,
                38435
            ],
            [
                66693,
                66693
            ],
            [
                6766,
                6766
            ],
            [
                39800,
                39800
            ],
            [
                15647,
                15647
            ],
            [
                73287,
                73287
            ],
            [
                29631,
                29631
            ],
            [
                67112,
                67112
            ],
            [
                62096,
                62096
            ],
            [
                71489,
                71489
            ],
            [
                71056,
                71056
            ],
            [
                23678,
                23678
            ],
            [
                33981,
                33981
            ],
            [
                18452,
                18452
            ]
        ],
        "range_type": "paragraph",
        "affected_metric": "coherence",
        "manipulation_category": "plot_inconsistencies",
        "manipulation_type": "temporal_inconsistencies",
        "gold_id": "JM-43546",
        "gold_text": "/data/project_gutenberg/gold_dataset/PG-43546.txt",
        "random_seed": 31,
        "params": {
            "n": 0,
            "min_len": 50,
            "repetition_factor": null,
            "start": 0,
            "end": 0,
            "ratio": true,
            "entity": null,
            "entities_to_consider": [
                "LOC",
                "GPE",
                "FAC",
                "ORG"
            ],
            "replacement_terms": [
                "stuff",
                "thing"
            ]
        }
    },
    {
        "id": "JM-645_C_2_24",
        "manipulated_text": "/data/project_gutenberg/manipulated_pg-1900_full/C/2/24/paragraph/exp_1/JM-645.txt",
        "manipulated_char_spans": [
            [
                22544,
                22544
            ],
            [
                21319,
                21319
            ],
            [
                20536,
                20536
            ],
            [
                79863,
                79863
            ],
            [
                69872,
                69872
            ],
            [
                78307,
                78307
            ],
            [
                22908,
                22908
            ],
            [
                22633,
                22633
            ],
            [
                78698,
                78698
            ],
            [
                82107,
                82107
            ],
            [
                20250,
                20250
            ],
            [
                48543,
                48543
            ],
            [
                58597,
                58597
            ],
            [
                80362,
                80362
            ],
            [
                23572,
                23572
            ],
            [
                80292,
                80292
            ]
        ],
        "range_type": "paragraph",
        "affected_metric": "coherence",
        "manipulation_category": "plot_inconsistencies",
        "manipulation_type": "temporal_inconsistencies",
        "gold_id": "JM-645",
        "gold_text": "/data/project_gutenberg/gold_dataset/PG-645.txt",
        "random_seed": 31,
        "params": {
            "n": 0,
            "min_len": 50,
            "repetition_factor": null,
            "start": 0,
            "end": 0,
            "ratio": true,
            "entity": null,
            "entities_to_consider": [
                "LOC",
                "GPE",
                "FAC",
                "ORG"
            ],
            "replacement_terms": [
                "stuff",
                "thing"
            ]
        }
    },
    {
        "id": "JM-42118_C_2_24",
        "manipulated_text": "/data/project_gutenberg/manipulated_pg-1900_full/C/2/24/paragraph/exp_1/JM-42118.txt",
        "manipulated_char_spans": [
            [
                56153,
                56153
            ],
            [
                62426,
                62426
            ],
            [
                43736,
                43736
            ],
            [
                19768,
                19768
            ],
            [
                11237,
                11237
            ],
            [
                36235,
                36235
            ],
            [
                22785,
                22785
            ],
            [
                10131,
                10131
            ],
            [
                15239,
                15239
            ],
            [
                3087,
                3087
            ],
            [
                8608,
                8608
            ],
            [
                44022,
                44022
            ]
        ],
        "range_type": "paragraph",
        "affected_metric": "coherence",
        "manipulation_category": "plot_inconsistencies",
        "manipulation_type": "temporal_inconsistencies",
        "gold_id": "JM-42118",
        "gold_text": "/data/project_gutenberg/gold_dataset/PG-42118.txt",
        "random_seed": 31,
        "params": {
            "n": 0,
            "min_len": 50,
            "repetition_factor": null,
            "start": 0,
            "end": 0,
            "ratio": true,
            "entity": null,
            "entities_to_consider": [
                "LOC",
                "GPE",
                "FAC",
                "ORG"
            ],
            "replacement_terms": [
                "stuff",
                "thing"
            ]
        }
    },
    {
        "id": "JM-20996_C_2_24",
        "manipulated_text": "/data/project_gutenberg/manipulated_pg-1900_full/C/2/24/paragraph/exp_1/JM-20996.txt",
        "manipulated_char_spans": [
            [
                5824,
                5824
            ],
            [
                3817,
                3817
            ],
            [
                24635,
                24635
            ],
            [
                10141,
                10141
            ],
            [
                31092,
                31092
            ],
            [
                19676,
                19676
            ],
            [
                41586,
                41586
            ],
            [
                2168,
                2168
            ],
            [
                21594,
                21594
            ],
            [
                4304,
                4304
            ]
        ],
        "range_type": "paragraph",
        "affected_metric": "coherence",
        "manipulation_category": "plot_inconsistencies",
        "manipulation_type": "temporal_inconsistencies",
        "gold_id": "JM-20996",
        "gold_text": "/data/project_gutenberg/gold_dataset/PG-20996.txt",
        "random_seed": 31,
        "params": {
            "n": 0,
            "min_len": 50,
            "repetition_factor": null,
            "start": 0,
            "end": 0,
            "ratio": true,
            "entity": null,
            "entities_to_consider": [
                "LOC",
                "GPE",
                "FAC",
                "ORG"
            ],
            "replacement_terms": [
                "stuff",
                "thing"
            ]
        }
    },
    {
        "id": "JM-14653_C_2_24",
        "manipulated_text": "/data/project_gutenberg/manipulated_pg-1900_full/C/2/24/paragraph/exp_1/JM-14653.txt",
        "manipulated_char_spans": [
            [
                23885,
                23885
            ],
            [
                53016,
                53016
            ],
            [
                40060,
                40060
            ],
            [
                34044,
                34044
            ],
            [
                44141,
                44141
            ],
            [
                37814,
                37814
            ],
            [
                38137,
                38137
            ],
            [
                62679,
                62679
            ],
            [
                55135,
                55135
            ],
            [
                17251,
                17251
            ],
            [
                25124,
                25124
            ]
        ],
        "range_type": "paragraph",
        "affected_metric": "coherence",
        "manipulation_category": "plot_inconsistencies",
        "manipulation_type": "temporal_inconsistencies",
        "gold_id": "JM-14653",
        "gold_text": "/data/project_gutenberg/gold_dataset/PG-14653.txt",
        "random_seed": 31,
        "params": {
            "n": 0,
            "min_len": 50,
            "repetition_factor": null,
            "start": 0,
            "end": 0,
            "ratio": true,
            "entity": null,
            "entities_to_consider": [
                "LOC",
                "GPE",
                "FAC",
                "ORG"
            ],
            "replacement_terms": [
                "stuff",
                "thing"
            ]
        }
    },
    {
        "id": "JM-45746_C_2_24",
        "manipulated_text": "/data/project_gutenberg/manipulated_pg-1900_full/C/2/24/paragraph/exp_1/JM-45746.txt",
        "manipulated_char_spans": [
            [
                55687,
                55687
            ],
            [
                28502,
                28502
            ],
            [
                49373,
                49373
            ],
            [
                23225,
                23225
            ],
            [
                62400,
                62400
            ],
            [
                26730,
                26730
            ],
            [
                17198,
                17198
            ],
            [
                66993,
                66993
            ],
            [
                33897,
                33897
            ],
            [
                41376,
                41376
            ],
            [
                4836,
                4836
            ],
            [
                31867,
                31867
            ]
        ],
        "range_type": "paragraph",
        "affected_metric": "coherence",
        "manipulation_category": "plot_inconsistencies",
        "manipulation_type": "temporal_inconsistencies",
        "gold_id": "JM-45746",
        "gold_text": "/data/project_gutenberg/gold_dataset/PG-45746.txt",
        "random_seed": 31,
        "params": {
            "n": 0,
            "min_len": 50,
            "repetition_factor": null,
            "start": 0,
            "end": 0,
            "ratio": true,
            "entity": null,
            "entities_to_consider": [
                "LOC",
                "GPE",
                "FAC",
                "ORG"
            ],
            "replacement_terms": [
                "stuff",
                "thing"
            ]
        }
    },
    {
        "id": "JM-59385_C_2_24",
        "manipulated_text": "/data/project_gutenberg/manipulated_pg-1900_full/C/2/24/paragraph/exp_1/JM-59385.txt",
        "manipulated_char_spans": [
            [
                10786,
                10786
            ],
            [
                48975,
                48975
            ],
            [
                13234,
                13234
            ],
            [
                56587,
                56587
            ],
            [
                50705,
                50705
            ],
            [
                70679,
                70679
            ],
            [
                43581,
                43581
            ],
            [
                35520,
                35520
            ],
            [
                19009,
                19009
            ],
            [
                7988,
                7988
            ],
            [
                38493,
                38493
            ],
            [
                41888,
                41888
            ],
            [
                18106,
                18106
            ]
        ],
        "range_type": "paragraph",
        "affected_metric": "coherence",
        "manipulation_category": "plot_inconsistencies",
        "manipulation_type": "temporal_inconsistencies",
        "gold_id": "JM-59385",
        "gold_text": "/data/project_gutenberg/gold_dataset/PG-59385.txt",
        "random_seed": 31,
        "params": {
            "n": 0,
            "min_len": 50,
            "repetition_factor": null,
            "start": 0,
            "end": 0,
            "ratio": true,
            "entity": null,
            "entities_to_consider": [
                "LOC",
                "GPE",
                "FAC",
                "ORG"
            ],
            "replacement_terms": [
                "stuff",
                "thing"
            ]
        }
    },
    {
        "id": "JM-51839_C_2_24",
        "manipulated_text": "/data/project_gutenberg/manipulated_pg-1900_full/C/2/24/paragraph/exp_1/JM-51839.txt",
        "manipulated_char_spans": [
            [
                5137,
                5137
            ],
            [
                38494,
                38494
            ],
            [
                60516,
                60516
            ],
            [
                51523,
                51523
            ],
            [
                24521,
                24521
            ],
            [
                29384,
                29384
            ],
            [
                11565,
                11565
            ],
            [
                5602,
                5602
            ],
            [
                62270,
                62270
            ],
            [
                46853,
                46853
            ],
            [
                58452,
                58452
            ]
        ],
        "range_type": "paragraph",
        "affected_metric": "coherence",
        "manipulation_category": "plot_inconsistencies",
        "manipulation_type": "temporal_inconsistencies",
        "gold_id": "JM-51839",
        "gold_text": "/data/project_gutenberg/gold_dataset/PG-51839.txt",
        "random_seed": 31,
        "params": {
            "n": 0,
            "min_len": 50,
            "repetition_factor": null,
            "start": 0,
            "end": 0,
            "ratio": true,
            "entity": null,
            "entities_to_consider": [
                "LOC",
                "GPE",
                "FAC",
                "ORG"
            ],
            "replacement_terms": [
                "stuff",
                "thing"
            ]
        }
    },
    {
        "id": "JM-28495_C_2_24",
        "manipulated_text": "/data/project_gutenberg/manipulated_pg-1900_full/C/2/24/paragraph/exp_1/JM-28495.txt",
        "manipulated_char_spans": [
            [
                9196,
                9196
            ],
            [
                9711,
                9711
            ],
            [
                7488,
                7488
            ],
            [
                8753,
                8753
            ],
            [
                13711,
                13711
            ],
            [
                40025,
                40025
            ],
            [
                45728,
                45728
            ],
            [
                36369,
                36369
            ],
            [
                40202,
                40202
            ],
            [
                12820,
                12820
            ]
        ],
        "range_type": "paragraph",
        "affected_metric": "coherence",
        "manipulation_category": "plot_inconsistencies",
        "manipulation_type": "temporal_inconsistencies",
        "gold_id": "JM-28495",
        "gold_text": "/data/project_gutenberg/gold_dataset/PG-28495.txt",
        "random_seed": 31,
        "params": {
            "n": 0,
            "min_len": 50,
            "repetition_factor": null,
            "start": 0,
            "end": 0,
            "ratio": true,
            "entity": null,
            "entities_to_consider": [
                "LOC",
                "GPE",
                "FAC",
                "ORG"
            ],
            "replacement_terms": [
                "stuff",
                "thing"
            ]
        }
    },
    {
        "id": "JM-41974_C_2_24",
        "manipulated_text": "/data/project_gutenberg/manipulated_pg-1900_full/C/2/24/paragraph/exp_1/JM-41974.txt",
        "manipulated_char_spans": [
            [
                27713,
                27713
            ],
            [
                816,
                816
            ],
            [
                15408,
                15408
            ],
            [
                20588,
                20588
            ],
            [
                11744,
                11744
            ],
            [
                35492,
                35492
            ],
            [
                14405,
                14405
            ],
            [
                18241,
                18241
            ]
        ],
        "range_type": "paragraph",
        "affected_metric": "coherence",
        "manipulation_category": "plot_inconsistencies",
        "manipulation_type": "temporal_inconsistencies",
        "gold_id": "JM-41974",
        "gold_text": "/data/project_gutenberg/gold_dataset/PG-41974.txt",
        "random_seed": 31,
        "params": {
            "n": 0,
            "min_len": 50,
            "repetition_factor": null,
            "start": 0,
            "end": 0,
            "ratio": true,
            "entity": null,
            "entities_to_consider": [
                "LOC",
                "GPE",
                "FAC",
                "ORG"
            ],
            "replacement_terms": [
                "stuff",
                "thing"
            ]
        }
    },
    {
        "id": "JM-48160_C_2_24",
        "manipulated_text": "/data/project_gutenberg/manipulated_pg-1900_full/C/2/24/paragraph/exp_1/JM-48160.txt",
        "manipulated_char_spans": [
            [
                3760,
                3760
            ],
            [
                38485,
                38485
            ],
            [
                41351,
                41351
            ],
            [
                57904,
                57904
            ],
            [
                55917,
                55917
            ],
            [
                42985,
                42985
            ],
            [
                76980,
                76980
            ],
            [
                55274,
                55274
            ],
            [
                30815,
                30815
            ],
            [
                46014,
                46014
            ],
            [
                29113,
                29113
            ],
            [
                15947,
                15947
            ],
            [
                61675,
                61675
            ],
            [
                37132,
                37132
            ],
            [
                80346,
                80346
            ]
        ],
        "range_type": "paragraph",
        "affected_metric": "coherence",
        "manipulation_category": "plot_inconsistencies",
        "manipulation_type": "temporal_inconsistencies",
        "gold_id": "JM-48160",
        "gold_text": "/data/project_gutenberg/gold_dataset/PG-48160.txt",
        "random_seed": 31,
        "params": {
            "n": 0,
            "min_len": 50,
            "repetition_factor": null,
            "start": 0,
            "end": 0,
            "ratio": true,
            "entity": null,
            "entities_to_consider": [
                "LOC",
                "GPE",
                "FAC",
                "ORG"
            ],
            "replacement_terms": [
                "stuff",
                "thing"
            ]
        }
    },
    {
        "id": "JM-50956_C_2_24",
        "manipulated_text": "/data/project_gutenberg/manipulated_pg-1900_full/C/2/24/paragraph/exp_1/JM-50956.txt",
        "manipulated_char_spans": [
            [
                53374,
                53374
            ],
            [
                22027,
                22027
            ],
            [
                46181,
                46181
            ],
            [
                47347,
                47347
            ],
            [
                34210,
                34210
            ],
            [
                20940,
                20940
            ],
            [
                40893,
                40893
            ],
            [
                48597,
                48597
            ],
            [
                14357,
                14357
            ],
            [
                58887,
                58887
            ]
        ],
        "range_type": "paragraph",
        "affected_metric": "coherence",
        "manipulation_category": "plot_inconsistencies",
        "manipulation_type": "temporal_inconsistencies",
        "gold_id": "JM-50956",
        "gold_text": "/data/project_gutenberg/gold_dataset/PG-50956.txt",
        "random_seed": 31,
        "params": {
            "n": 0,
            "min_len": 50,
            "repetition_factor": null,
            "start": 0,
            "end": 0,
            "ratio": true,
            "entity": null,
            "entities_to_consider": [
                "LOC",
                "GPE",
                "FAC",
                "ORG"
            ],
            "replacement_terms": [
                "stuff",
                "thing"
            ]
        }
    },
    {
        "id": "JM-37513_C_2_24",
        "manipulated_text": "/data/project_gutenberg/manipulated_pg-1900_full/C/2/24/paragraph/exp_1/JM-37513.txt",
        "manipulated_char_spans": [
            [
                74781,
                74781
            ],
            [
                62089,
                62089
            ],
            [
                33762,
                33762
            ],
            [
                22221,
                22221
            ],
            [
                52069,
                52069
            ],
            [
                6196,
                6196
            ],
            [
                2815,
                2815
            ],
            [
                76466,
                76466
            ],
            [
                55555,
                55555
            ],
            [
                36585,
                36585
            ],
            [
                35113,
                35113
            ],
            [
                20228,
                20228
            ],
            [
                28191,
                28191
            ]
        ],
        "range_type": "paragraph",
        "affected_metric": "coherence",
        "manipulation_category": "plot_inconsistencies",
        "manipulation_type": "temporal_inconsistencies",
        "gold_id": "JM-37513",
        "gold_text": "/data/project_gutenberg/gold_dataset/PG-37513.txt",
        "random_seed": 31,
        "params": {
            "n": 0,
            "min_len": 50,
            "repetition_factor": null,
            "start": 0,
            "end": 0,
            "ratio": true,
            "entity": null,
            "entities_to_consider": [
                "LOC",
                "GPE",
                "FAC",
                "ORG"
            ],
            "replacement_terms": [
                "stuff",
                "thing"
            ]
        }
    },
    {
        "id": "JM-41939_C_2_24",
        "manipulated_text": "/data/project_gutenberg/manipulated_pg-1900_full/C/2/24/paragraph/exp_1/JM-41939.txt",
        "manipulated_char_spans": [
            [
                17416,
                17416
            ],
            [
                36711,
                36711
            ],
            [
                29962,
                29962
            ],
            [
                21324,
                21324
            ],
            [
                7755,
                7755
            ],
            [
                49495,
                49495
            ],
            [
                7989,
                7989
            ],
            [
                44304,
                44304
            ],
            [
                47835,
                47835
            ]
        ],
        "range_type": "paragraph",
        "affected_metric": "coherence",
        "manipulation_category": "plot_inconsistencies",
        "manipulation_type": "temporal_inconsistencies",
        "gold_id": "JM-41939",
        "gold_text": "/data/project_gutenberg/gold_dataset/PG-41939.txt",
        "random_seed": 31,
        "params": {
            "n": 0,
            "min_len": 50,
            "repetition_factor": null,
            "start": 0,
            "end": 0,
            "ratio": true,
            "entity": null,
            "entities_to_consider": [
                "LOC",
                "GPE",
                "FAC",
                "ORG"
            ],
            "replacement_terms": [
                "stuff",
                "thing"
            ]
        }
    },
    {
        "id": "JM-43068_C_2_24",
        "manipulated_text": "/data/project_gutenberg/manipulated_pg-1900_full/C/2/24/paragraph/exp_1/JM-43068.txt",
        "manipulated_char_spans": [
            [
                1949,
                1949
            ],
            [
                38914,
                38914
            ],
            [
                49971,
                49971
            ],
            [
                38048,
                38048
            ],
            [
                25387,
                25387
            ],
            [
                48499,
                48499
            ],
            [
                56566,
                56566
            ],
            [
                51517,
                51517
            ],
            [
                8492,
                8492
            ],
            [
                35109,
                35109
            ]
        ],
        "range_type": "paragraph",
        "affected_metric": "coherence",
        "manipulation_category": "plot_inconsistencies",
        "manipulation_type": "temporal_inconsistencies",
        "gold_id": "JM-43068",
        "gold_text": "/data/project_gutenberg/gold_dataset/PG-43068.txt",
        "random_seed": 31,
        "params": {
            "n": 0,
            "min_len": 50,
            "repetition_factor": null,
            "start": 0,
            "end": 0,
            "ratio": true,
            "entity": null,
            "entities_to_consider": [
                "LOC",
                "GPE",
                "FAC",
                "ORG"
            ],
            "replacement_terms": [
                "stuff",
                "thing"
            ]
        }
    },
    {
        "id": "JM-43085_C_2_24",
        "manipulated_text": "/data/project_gutenberg/manipulated_pg-1900_full/C/2/24/paragraph/exp_1/JM-43085.txt",
        "manipulated_char_spans": [
            [
                50605,
                50605
            ],
            [
                1216,
                1216
            ],
            [
                26515,
                26515
            ],
            [
                11036,
                11036
            ],
            [
                42170,
                42170
            ],
            [
                34754,
                34754
            ],
            [
                20439,
                20439
            ],
            [
                43580,
                43580
            ],
            [
                31855,
                31855
            ]
        ],
        "range_type": "paragraph",
        "affected_metric": "coherence",
        "manipulation_category": "plot_inconsistencies",
        "manipulation_type": "temporal_inconsistencies",
        "gold_id": "JM-43085",
        "gold_text": "/data/project_gutenberg/gold_dataset/PG-43085.txt",
        "random_seed": 31,
        "params": {
            "n": 0,
            "min_len": 50,
            "repetition_factor": null,
            "start": 0,
            "end": 0,
            "ratio": true,
            "entity": null,
            "entities_to_consider": [
                "LOC",
                "GPE",
                "FAC",
                "ORG"
            ],
            "replacement_terms": [
                "stuff",
                "thing"
            ]
        }
    },
    {
        "id": "JM-3256_C_2_24",
        "manipulated_text": "/data/project_gutenberg/manipulated_pg-1900_full/C/2/24/paragraph/exp_1/JM-3256.txt",
        "manipulated_char_spans": [
            [
                48129,
                48129
            ],
            [
                45198,
                45198
            ],
            [
                35746,
                35746
            ],
            [
                16954,
                16954
            ],
            [
                33178,
                33178
            ],
            [
                25015,
                25015
            ],
            [
                206,
                206
            ],
            [
                4448,
                4448
            ],
            [
                19357,
                19357
            ]
        ],
        "range_type": "paragraph",
        "affected_metric": "coherence",
        "manipulation_category": "plot_inconsistencies",
        "manipulation_type": "temporal_inconsistencies",
        "gold_id": "JM-3256",
        "gold_text": "/data/project_gutenberg/gold_dataset/PG-3256.txt",
        "random_seed": 31,
        "params": {
            "n": 0,
            "min_len": 50,
            "repetition_factor": null,
            "start": 0,
            "end": 0,
            "ratio": true,
            "entity": null,
            "entities_to_consider": [
                "LOC",
                "GPE",
                "FAC",
                "ORG"
            ],
            "replacement_terms": [
                "stuff",
                "thing"
            ]
        }
    },
    {
        "id": "JM-3148_C_2_24",
        "manipulated_text": "/data/project_gutenberg/manipulated_pg-1900_full/C/2/24/paragraph/exp_1/JM-3148.txt",
        "manipulated_char_spans": [
            [
                56414,
                56414
            ],
            [
                22064,
                22064
            ],
            [
                304,
                304
            ],
            [
                18867,
                18867
            ],
            [
                22319,
                22319
            ],
            [
                53339,
                53339
            ],
            [
                24244,
                24244
            ],
            [
                27293,
                27293
            ],
            [
                49932,
                49932
            ],
            [
                60257,
                60257
            ],
            [
                49421,
                49421
            ],
            [
                55484,
                55484
            ],
            [
                67635,
                67635
            ],
            [
                58359,
                58359
            ],
            [
                23396,
                23396
            ]
        ],
        "range_type": "paragraph",
        "affected_metric": "coherence",
        "manipulation_category": "plot_inconsistencies",
        "manipulation_type": "temporal_inconsistencies",
        "gold_id": "JM-3148",
        "gold_text": "/data/project_gutenberg/gold_dataset/PG-3148.txt",
        "random_seed": 31,
        "params": {
            "n": 0,
            "min_len": 50,
            "repetition_factor": null,
            "start": 0,
            "end": 0,
            "ratio": true,
            "entity": null,
            "entities_to_consider": [
                "LOC",
                "GPE",
                "FAC",
                "ORG"
            ],
            "replacement_terms": [
                "stuff",
                "thing"
            ]
        }
    },
    {
        "id": "JM-13890_C_2_24",
        "manipulated_text": "/data/project_gutenberg/manipulated_pg-1900_full/C/2/24/paragraph/exp_1/JM-13890.txt",
        "manipulated_char_spans": [
            [
                4095,
                4095
            ],
            [
                22726,
                22726
            ],
            [
                55206,
                55206
            ],
            [
                49977,
                49977
            ],
            [
                9766,
                9766
            ],
            [
                18882,
                18882
            ],
            [
                20626,
                20626
            ],
            [
                54843,
                54843
            ],
            [
                47452,
                47452
            ],
            [
                14492,
                14492
            ],
            [
                17574,
                17574
            ],
            [
                23984,
                23984
            ]
        ],
        "range_type": "paragraph",
        "affected_metric": "coherence",
        "manipulation_category": "plot_inconsistencies",
        "manipulation_type": "temporal_inconsistencies",
        "gold_id": "JM-13890",
        "gold_text": "/data/project_gutenberg/gold_dataset/PG-13890.txt",
        "random_seed": 31,
        "params": {
            "n": 0,
            "min_len": 50,
            "repetition_factor": null,
            "start": 0,
            "end": 0,
            "ratio": true,
            "entity": null,
            "entities_to_consider": [
                "LOC",
                "GPE",
                "FAC",
                "ORG"
            ],
            "replacement_terms": [
                "stuff",
                "thing"
            ]
        }
    },
    {
        "id": "JM-25809_C_2_24",
        "manipulated_text": "/data/project_gutenberg/manipulated_pg-1900_full/C/2/24/paragraph/exp_1/JM-25809.txt",
        "manipulated_char_spans": [
            [
                22717,
                22717
            ],
            [
                63916,
                63916
            ],
            [
                14549,
                14549
            ],
            [
                8228,
                8228
            ],
            [
                12672,
                12672
            ],
            [
                56568,
                56568
            ],
            [
                56429,
                56429
            ],
            [
                885,
                885
            ],
            [
                73780,
                73780
            ],
            [
                75370,
                75370
            ],
            [
                25336,
                25336
            ],
            [
                63426,
                63426
            ],
            [
                57541,
                57541
            ],
            [
                41553,
                41553
            ],
            [
                62844,
                62844
            ]
        ],
        "range_type": "paragraph",
        "affected_metric": "coherence",
        "manipulation_category": "plot_inconsistencies",
        "manipulation_type": "temporal_inconsistencies",
        "gold_id": "JM-25809",
        "gold_text": "/data/project_gutenberg/gold_dataset/PG-25809.txt",
        "random_seed": 31,
        "params": {
            "n": 0,
            "min_len": 50,
            "repetition_factor": null,
            "start": 0,
            "end": 0,
            "ratio": true,
            "entity": null,
            "entities_to_consider": [
                "LOC",
                "GPE",
                "FAC",
                "ORG"
            ],
            "replacement_terms": [
                "stuff",
                "thing"
            ]
        }
    }
]